pyDecision/__init__.py
pyDecision/algorithm/__init__.py
pyDecision/algorithm/ahp.py
pyDecision/algorithm/anp.py
pyDecision/algorithm/aras.py
pyDecision/algorithm/borda.py
pyDecision/algorithm/bwm.py
pyDecision/algorithm/bwm_s.py
pyDecision/algorithm/cilos.py
pyDecision/algorithm/cocoso.py
pyDecision/algorithm/codas.py
pyDecision/algorithm/copeland.py
pyDecision/algorithm/copras.py
pyDecision/algorithm/cpp_tri.py
pyDecision/algorithm/cradis.py
pyDecision/algorithm/critic.py
pyDecision/algorithm/dematel.py
pyDecision/algorithm/e_i.py
pyDecision/algorithm/e_i_s.py
pyDecision/algorithm/e_i_v.py
pyDecision/algorithm/e_ii.py
pyDecision/algorithm/e_iii.py
pyDecision/algorithm/e_iv.py
pyDecision/algorithm/e_tri_b.py
pyDecision/algorithm/e_tri_c.py
pyDecision/algorithm/e_tri_nc.py
pyDecision/algorithm/edas.py
pyDecision/algorithm/entropy.py
pyDecision/algorithm/flowsort.py
pyDecision/algorithm/fucom.py
pyDecision/algorithm/fuzzy_ahp.py
pyDecision/algorithm/fuzzy_ahp_ppf.py
pyDecision/algorithm/fuzzy_aras.py
pyDecision/algorithm/fuzzy_bwm.py
pyDecision/algorithm/fuzzy_copras.py
pyDecision/algorithm/fuzzy_critic.py
pyDecision/algorithm/fuzzy_dematel.py
pyDecision/algorithm/fuzzy_edas.py
pyDecision/algorithm/fuzzy_fucom.py
pyDecision/algorithm/fuzzy_merec.py
pyDecision/algorithm/fuzzy_moora.py
pyDecision/algorithm/fuzzy_ocra.py
pyDecision/algorithm/fuzzy_topsis.py
pyDecision/algorithm/fuzzy_vikor.py
pyDecision/algorithm/fuzzy_waspas.py
pyDecision/algorithm/gra.py
pyDecision/algorithm/idocriw.py
pyDecision/algorithm/lmaw.py
pyDecision/algorithm/mabac.py
pyDecision/algorithm/macbeth.py
pyDecision/algorithm/mairca.py
pyDecision/algorithm/mara.py
pyDecision/algorithm/marcos.py
pyDecision/algorithm/maut.py
pyDecision/algorithm/merec.py
pyDecision/algorithm/moora.py
pyDecision/algorithm/moosra.py
pyDecision/algorithm/multimoora.py
pyDecision/algorithm/ocra.py
pyDecision/algorithm/opa.py
pyDecision/algorithm/oreste.py
pyDecision/algorithm/p_ec.py
pyDecision/algorithm/p_i.py
pydecision-4.8.2.dist-info/LICENSE
pydecision-4.8.2.dist-info/METADATA
pydecision-4.8.2.dist-info/WHEEL
pydecision-4.8.2.dist-info/top_level.txt
pydecision-4.8.2.dist-info/RECORD
