Metadata-Version: 2.1
Name: pydecision
Version: 4.8.2
Summary: A MCDA Library Incorporating a Large Language Model to Enhance Decision Analysis
Home-page: https://github.com/Valdecy/pyDecisions
Author: Valdecy Pereira
Author-email: valdecy.pereira@gmail.com
License: GNU
License-File: LICENSE
Requires-Dist: llmx
Requires-Dist: matplotlib
Requires-Dist: numpy
Requires-Dist: openai
Requires-Dist: pandas
Requires-Dist: scikit-learn
Requires-Dist: scipy
